{
  "id": "atomic-overwrite-1756680584475",
  "title": "Overwrite Test Updated",
  "body": "Updated body @ 1756680584504",
  "priority": 50,
  "audience": "all",
  "requirement": "optional",
  "categories": [],
  "sourceHash": "0cfc48d8608067da7aa8b9cb6b0819d71398e5020ad439154b85ced8a16a5791",
  "schemaVersion": "2",
  "createdAt": "2025-08-31T22:49:44.477Z",
  "updatedAt": "2025-08-31T22:49:44.505Z",
  "riskScore": 55,
  "version": "1.0.0",
  "status": "approved",
  "owner": "unowned",
  "priorityTier": "P3",
  "classification": "internal",
  "lastReviewedAt": "2025-08-31T22:49:44.477Z",
  "nextReviewDue": "2025-11-29T22:49:44.477Z",
  "reviewIntervalDays": 90,
  "changeLog": [
    {
      "version": "1.0.0",
      "changedAt": "2025-08-31T22:49:44.477Z",
      "summary": "initial import"
    }
  ],
  "semanticSummary": "Initial body"
}