{
  "id": "gov-hash-skip-1756811143373",
  "title": "gov-hash-skip-1756811143373",
  "body": "governance-body-static-v2",
  "priority": 50,
  "audience": "all",
  "requirement": "optional",
  "categories": [],
  "sourceHash": "fc5be0b780e44c15f081b62133738fabc7dc045231a2e4c57efc79a4ad63a60f",
  "schemaVersion": "3",
  "createdAt": "2025-09-02T11:05:43.375Z",
  "updatedAt": "2025-09-02T11:05:44.147Z",
  "riskScore": 55,
  "version": "1.0.0",
  "status": "approved",
  "owner": "unowned",
  "priorityTier": "P3",
  "classification": "internal",
  "lastReviewedAt": "2025-09-02T11:05:43.376Z",
  "nextReviewDue": "2025-12-01T11:05:43.376Z",
  "reviewIntervalDays": 90,
  "changeLog": [
    {
      "version": "1.0.0",
      "changedAt": "2025-09-02T11:05:43.375Z",
      "summary": "initial import"
    }
  ],
  "semanticSummary": "governance-body-static-v1"
}