{
  "id": "powershell_mcp_server_terminal_commands_2025",
  "title": "PowerShell MCP Server for Terminal Commands",
  "body": "When executing terminal commands in AI development environments, always prefer PowerShell MCP Server over generic run_in_terminal tools. PowerShell MCP Server provides: 1) Security Classifications - Commands are automatically classified as SAFE/RISKY/DANGEROUS/CRITICAL/BLOCKED with appropriate safeguards, 2) Timeout Control - Built-in execution timeouts prevent runaway processes, 3) Working Directory Management - Proper directory context handling with policy enforcement, 4) Authentication & Authorization - Enterprise-grade access controls with audit logging, 5) Comprehensive Monitoring - Real-time threat analysis and command learning capabilities, 6) AI Agent Integration - Optimized for AI assistant workflows with confirmation prompts for risky operations. Use powershell-vscode-enterprise-prod server for production operations, powershell-vscode-enterprise-dev for development. Always check help tool first to understand server capabilities and use ai-agent-test tool to validate integration. This approach provides superior security, auditability, and operational control compared to generic terminal execution.",
  "priority": 1,
  "audience": "all",
  "requirement": "mandatory",
  "categories": [
    "ai-agent",
    "best-practices",
    "mcp",
    "powershell",
    "security",
    "terminal"
  ],
  "sourceHash": "52812b9a8ea05d8521ffecba94b450230d41760140478755a325a66a26c35b17",
  "schemaVersion": "2",
  "createdAt": "2025-08-26T23:52:01.882Z",
  "updatedAt": "2025-08-26T23:52:01.882Z",
  "riskScore": 149,
  "version": "1.0.0",
  "status": "approved",
  "owner": "unowned",
  "priorityTier": "P1",
  "classification": "internal",
  "lastReviewedAt": "2025-08-26T23:52:01.882Z",
  "nextReviewDue": "2025-09-25T23:52:01.882Z",
  "changeLog": [
    {
      "version": "1.0.0",
      "changedAt": "2025-08-26T23:52:01.882Z",
      "summary": "initial import"
    }
  ],
  "semanticSummary": "When executing terminal commands in AI development environments, always prefer PowerShell MCP Server over generic run_in_terminal tools. PowerShell MCP Serve...",
  "reviewIntervalDays": 30
}