{
  "timestamp": 1758210800460,
  "server": {
    "uptime": 540066,
    "version": "1.6.0",
    "memoryUsage": {
      "rss": 63217664,
      "heapTotal": 17858560,
      "heapUsed": 16295256,
      "external": 2572750,
      "arrayBuffers": 57613
    },
    "cpuUsage": {
      "user": 0,
      "system": 0
    },
    "startTime": 1758210260394
  },
  "tools": {
    "http/request": {
      "callCount": 74,
      "successCount": 74,
      "errorCount": 0,
      "totalResponseTime": 114.32100000000004,
      "errorTypes": {},
      "lastCalled": 1758210752377
    }
  },
  "connections": {
    "activeConnections": 2,
    "totalConnections": 2,
    "disconnectedConnections": 0,
    "avgSessionDuration": 536669.5
  },
  "performance": {
    "requestsPerMinute": 8,
    "successRate": 100,
    "avgResponseTime": 1.5448783783783788,
    "errorRate": 0
  }
}